cints.cpython-38-x86_64-linux-gnu.so
AFLOWpi-1.3.1.dist-info/METADATA
AFLOWpi-1.3.1.dist-info/RECORD
AFLOWpi-1.3.1.dist-info/top_level.txt
AFLOWpi-1.3.1.dist-info/WHEEL
AFLOWpi/__init__.py
AFLOWpi/aflowlib/aflowlib.py
AFLOWpi/aflowlib/__init__.py
AFLOWpi/aflowlib/parse_aflowlib.py
AFLOWpi/aflowlib/machine_info.py
AFLOWpi/aflowlib/pseudo_info.py
AFLOWpi/run/sound_velocity.py
AFLOWpi/run/elastic.py
AFLOWpi/run/post_proc.py
AFLOWpi/run/submission_daemon.py
AFLOWpi/run/raman_spectra.py
AFLOWpi/run/epsilon.py
AFLOWpi/run/__init__.py
AFLOWpi/run/fd_phonon_sym.py
AFLOWpi/run/fd_fields.py
AFLOWpi/run/run.py
AFLOWpi/run/IR_spectra.py
AFLOWpi/run/converge_smearing.py
AFLOWpi/run/phonon.py
AFLOWpi/qe/__init__.py
AFLOWpi/qe/regex.py
AFLOWpi/retr/load_dyn.py
AFLOWpi/retr/supercell.py
AFLOWpi/retr/thermal.py
AFLOWpi/retr/get_cif_aflow.py
AFLOWpi/retr/gap_tools.py
AFLOWpi/retr/rdf.py
AFLOWpi/retr/__init__.py
AFLOWpi/retr/retr.py
AFLOWpi/retr/get_high_sym_points.py
AFLOWpi/scfuj/read_hubbard_orbs.py
AFLOWpi/scfuj/paopy_interface.py
AFLOWpi/scfuj/__init__.py
AFLOWpi/scfuj/UPF_gaussfit.py
AFLOWpi/scfuj/scfuj.py
AFLOWpi/scfuj/acbn0_support/integs.py
AFLOWpi/scfuj/acbn0_support/acbn0.py
AFLOWpi/scfuj/acbn0_support/pyints.py
AFLOWpi/scfuj/acbn0_support/Molecule.py
AFLOWpi/prep/isotropy.py
AFLOWpi/prep/substep.py
AFLOWpi/prep/setup_iterative.py
AFLOWpi/prep/aflow_wyckoff.py
AFLOWpi/prep/prep.py
AFLOWpi/prep/process_cif_sym.py
AFLOWpi/prep/__init__.py
AFLOWpi/prep/get_step.py
AFLOWpi/prep/shake.py
AFLOWpi/prep/standardize_alat.py
AFLOWpi/prep/k_points.py
AFLOWpi/prep/tb_prep.py
AFLOWpi/prep/cDFT_oxy.py
AFLOWpi/prep/berry.py
AFLOWpi/elph/do_read_modes.py
AFLOWpi/elph/__init__.py
AFLOWpi/elph/elph_setup.py
AFLOWpi/environ/config.py
AFLOWpi/environ/environment.py
AFLOWpi/environ/__init__.py
AFLOWpi/environ/input.py
AFLOWpi/environ/environ.py
AFLOWpi/environ/default.py
AFLOWpi/AFLOWSYM/aflow
AFLOWpi/AFLOWSYM/aflow_sym.py
AFLOWpi/pseudo/qe_to_exciting.py
AFLOWpi/pseudo/__init__.py
AFLOWpi/pseudo/pseudo.py
AFLOWpi/PAOFLOW/examples/main.py
