Metadata-Version: 2.1
Name: AFLOWpi
Version: 1.3.1
Summary: Medium Throughput Framework for Quantum Espresso
Home-page: http://aflowlib.org/src/aflowpi/
Author: Andrew Supka,Marco Fornari
Author-email: supka1ar@cmich.edu
License: UNKNOWN
Platform: manylinux_2_24
Platform: manylinux2014
Requires-Dist: matplotlib
Requires-Dist: PAOFLOW (==2.0.18)
